codecat_pypatric/classes.py
codecat_pypatric/deck_tools.py
codecat_pypatric/electric.py
codecat_pypatric/keys.py
codecat_pypatric/magnetic.py
codecat_pypatric/units.py
codecat_pypatric-1.0.dist-info/METADATA
codecat_pypatric-1.0.dist-info/WHEEL
codecat_pypatric-1.0.dist-info/top_level.txt
codecat_pypatric-1.0.dist-info/RECORD
