Metadata-Version: 2.1
Name: codecat_pypatric
Version: 1.0
Summary: Helper package for the PaTriC particle tracking code.
Home-page: https://github.com/hafizmdyasir/codecat_pypatric
Author: Mohammad Yasir
Author-email: yasir.iitd@outlook.com
License: GNU GPL Version 3
